diamond/__init__.py
diamond/collector.py
diamond/convertor.py
diamond/error.py
diamond/gmetric.py
diamond/metric.py
diamond/server.py
diamond/util.py
diamond/version.py
diamond/handler/Handler.py
diamond/handler/__init__.py
diamond/handler/archive.py
diamond/handler/cloudwatch.py
diamond/handler/datadog.py
diamond/handler/g_metric.py
diamond/handler/graphite.py
diamond/handler/graphitepickle.py
diamond/handler/hostedgraphite.py
diamond/handler/httpHandler.py
diamond/handler/influxdbHandler.py
diamond/handler/libratohandler.py
diamond/handler/logentries_diamond.py
diamond/handler/mqtt.py
diamond/handler/multigraphite.py
diamond/handler/multigraphitepickle.py
diamond/handler/mysql.py
diamond/handler/null.py
diamond/handler/queue.py
diamond/handler/rabbitmq_pubsub.py
diamond/handler/rabbitmq_topic.py
diamond/handler/riemann.py
diamond/handler/rrdtool.py
diamond/handler/sentry.py
diamond/handler/signalfx.py
diamond/handler/stats_d.py
diamond/handler/statsite.py
diamond/handler/tsdb.py
diamond/handler/zmq_pubsub.py
diamond/utils/__init__.py
diamond/utils/classes.py
diamond/utils/config.py
diamond/utils/log.py
diamond/utils/scheduler.py
diamond/utils/signals.py
diamond-4.0.501.data/data/share/diamond/LICENSE
diamond-4.0.501.data/data/share/diamond/version.txt
diamond-4.0.501.data/data/share/diamond/collectors/amavis/amavis.py
diamond-4.0.501.data/data/share/diamond/collectors/apcupsd/apcupsd.py
diamond-4.0.501.data/data/share/diamond/collectors/aurora/aurora.py
diamond-4.0.501.data/data/share/diamond/collectors/beanstalkd/beanstalkd.py
diamond-4.0.501.data/data/share/diamond/collectors/bind/bind.py
diamond-4.0.501.data/data/share/diamond/collectors/celerymon/celerymon.py
diamond-4.0.501.data/data/share/diamond/collectors/ceph/ceph.py
diamond-4.0.501.data/data/share/diamond/collectors/cephstats/cephstats.py
diamond-4.0.501.data/data/share/diamond/collectors/chronyd/chronyd.py
diamond-4.0.501.dist-info/DESCRIPTION.rst
diamond-4.0.501.dist-info/METADATA
diamond-4.0.501.dist-info/RECORD
diamond-4.0.501.dist-info/WHEEL
diamond-4.0.501.dist-info/metadata.json
diamond-4.0.501.dist-info/top_level.txt
