Metadata-Version: 2.0
Name: diamond
Version: 4.0.501
Summary: Smart data producer for graphite graphing package
Home-page: https://github.com/python-diamond/Diamond
Author: The Diamond Team
Author-email: diamond@librelist.com
License: MIT License
Platform: UNKNOWN
Classifier: Programming Language :: Python
Classifier: Programming Language :: Python :: 2
Requires-Dist: configobj
Requires-Dist: psutil
